{"chunk_definitions":[{"row":174,"row_count":1,"visible":true,"expansion_state":0,"options":{"engine":"r","fig.width":11,"height":10,"label":"unnamed-chunk-64"},"document_id":"95570068","chunk_id":"ce1lsle4d30md","chunk_label":"unnamed-chunk-8"},{"row":206,"row_count":1,"visible":true,"expansion_state":0,"options":{"engine":"r","label":"unnamed-chunk-61"},"document_id":"95570068","chunk_id":"cr5yw5h4mh3ko","chunk_label":"unnamed-chunk-9"},{"row":233,"row_count":1,"visible":true,"expansion_state":0,"options":{"engine":"r","label":"unnamed-chunk-41"},"document_id":"95570068","chunk_id":"cjbo0p12sazbu","chunk_label":"unnamed-chunk-10"}],"doc_write_time":1663191176}